Workbook

Sheet Annahmen
A1: Capybara Media — Wirtschafts-Annahmen (Text-Etage, MVP-Modell)
A3: Alle blauen Zellen sind Eingaben — hier änderst du Werte, um Balance zu testen.
A5: Start-Kapital | B5: 500 | C5: Geld zu Spielbeginn
A6: Start-Reichweite | B6: 100 | C6: Reichweite zu Spielbeginn
A7: Start-Reputation (0-100) | B7: 50 | C7: Reputation zu Spielbeginn
A8: Start-Abonnenten | B8: 20 | C8: Abonnenten zu Spielbeginn
A9: Preis pro Abo | B9: 2 | C9: Erlös pro Abonnent und Tag
A10: Basis-Werbepreis pro Reichweiten-Einheit (bei Reputation=100) | B10: 0.05 | C10: Skaliert mit aktueller Reputation/100
A11: Konversionsrate-Basis (bei Reputation=100) | B11: 0.3 | C11: Anteil der Reichweite, der potenziell Abo wird
A12: Anpassungsrate Abonnenten (Trägheit) | B12: 0.15 | C12: Wie schnell sich Abo-Zahl an Ziel anpasst, s. Design-Dok Abschnitt 5
A13: Reichweiten-Zerfall pro Tag | B13: 0.03 | C13: Anteil, der täglich ohne neue Story verloren geht
A14: Reputations-Mean-Reversion-Rate | B14: 0.05 | C14: Zieht Reputation pro Tag leicht Richtung 50 zurück
A15: Basis-Reichweitenzuwachs pro Story | B15: 20 | C15: Reichweitengewinn einer Durchschnitts-Story
A16: Boulevard-Reichweiten-Bonusfaktor | B16: 0.15 | C16: Wie stark Grad 5 vs. Grad 3 die Reichweite erhöht
... A27: Abwechslungs-Bonusfaktor Reputation | B27: 2.5 | C27: Wirkung von Abweichung vom eigenen Durchschnitt auf Reputation

Sheet Sim_Boulevard
A1: Tag | B1: Boulevard-Grad | C1: Reichweite | D1: Reputation | E1: Abonnenten | F1: Werbe-Erlös | G1: Abo-Erlös | H1: Kosten | I1: Gewinn | J1: Kontostand | K1: Gleitender Ø-Grad | L1: Abwechslung |Grad-Ø|
A2: 1 | B2: 5 | C2: =Annahmen!$B$6*(1-Annahmen!$B$13)+Annahmen!$B$15*(1+(B2-3)/2*Annahmen!$B$16)*(1+Annahmen!$B$25*(L2-Annahmen!$B$26)) -> 108.5 | D2: =MIN(100,MAX(0,Annahmen!$B$7-Annahmen!$B$17*(B2-3)-Annahmen!$B$14*(Annahmen!$B$7-50)+Annahmen!$B$27*(L2-Annahmen!$B$26))) -> 44.5 | E2: =Annahmen!$B$8+Annahmen!$B$12*(C2*Annahmen!$B$11*(D2/100)-Annahmen!$B$8) -> 19.172712 | F2: =C2*Annahmen!$B$10*(D2/100) -> 2.414125 | G2: =E2*Annahmen!$B$9 -> 38.345425 | H2: =Annahmen!$B$18*Annahmen!$B$20*Annahmen!$B$19+Annahmen!$B$21+C2*Annahmen!$B$22 -> 88.085 | I2: =F2+G2-H2 -> -47.32545 | J2: =Annahmen!$B$5+I2 -> 452.67455 | K2: 0 | L2: 0
A3: 2 | B3: 5 | C3: =C2*(1-Annahmen!$B$13)+Annahmen!$B$15*(1+(B3-3)/2*Annahmen!$B$16)*(1+Annahmen!$B$25*(L3-Annahmen!$B$26)) -> 116.745 | D3: =MIN(100,MAX(0,D2-Annahmen!$B$17*(B3-3)-Annahmen!$B$14*(D2-50)+Annahmen!$B$27*(L3-Annahmen!$B$26))) -> 39.275 | E3: =E2+Annahmen!$B$12*(C3*Annahmen!$B$11*(D3/100)-E2) -> 18.360128 | F3: =C3*Annahmen!$B$10*(D3/100) -> 2.2925799 | G3: =E3*Annahmen!$B$9 -> 36.720255 | H3: =Annahmen!$B$18*Annahmen!$B$20*Annahmen!$B$19+Annahmen!$B$21+C3*Annahmen!$B$22 -> 88.16745 | I3: =F3+G3-H3 -> -49.154615 | J3: =J2+I3 -> 403.51994 | K3: =AVERAGE(B2:B2) -> 5 | L3: =ABS(B3-K3) -> 0
A4: 3 | B4: 5 | C4: =C3*(1-Annahmen!$B$13)+Annahmen!$B$15*(1+(B4-3)/2*Annahmen!$B$16)*(1+Annahmen!$B$25*(L4-Annahmen!$B$26)) -> 124.74265 | D4: =MIN(100,MAX(0,D3-Annahmen!$B$17*(B4-3)-Annahmen!$B$14*(D3-50)+Annahmen!$B$27*(L4-Annahmen!$B$26))) -> 34.31125 | E4: =E3+Annahmen!$B$12*(C4*Annahmen!$B$11*(D4/100)-E3) -> 17.532143 | F4: =C4*Annahmen!$B$10*(D4/100) -> 2.1400381 | G4: =E4*Annahmen!$B$9 -> 35.064285 | H4: =Annahmen!$B$18*Annahmen!$B$20*Annahmen!$B$19+Annahmen!$B$21+C4*Annahmen!$B$22 -> 88.247427 | I4: =F4+G4-H4 -> -51.043103 | J4: =J3+I4 -> 352.47683 | K4: =AVERAGE(B2:B3) -> 5 | L4: =ABS(B4-K4) -> 0
A5: 4 | B5: 5 | C5: =C4*(1-Annahmen!$B$13)+Annahmen!$B$15*(1+(B5-3)/2*Annahmen!$B$16)*(1+Annahmen!$B$25*(L5-Annahmen!$B$26)) -> 132.50037 | D5: =MIN(100,MAX(0,D4-Annahmen!$B$17*(B5-3)-Annahmen!$B$14*(D4-50)+Annahmen!$B$27*(L5-Annahmen!$B$26))) -> 29.595688 | E5: =E4+Annahmen!$B$12*(C5*Annahmen!$B$11*(D5/100)-E4) -> 16.666969 | F5: =C5*Annahmen!$B$10*(D5/100) -> 1.9607198 | G5: =E5*Annahmen!$B$9 -> 33.333938 | H5: =Annahmen!$B$18*Annahmen!$B$20*Annahmen!$B$19+Annahmen!$B$21+C5*Annahmen!$B$22 -> 88.325004 | I5: =F5+G5-H5 -> -53.030346 | J5: =J4+I5 -> 299.44649 | K5: =AVERAGE(B2:B4) -> 5 | L5: =ABS(B5-K5) -> 0
A6: 5 | B6: 5 | C6: =C5*(1-Annahmen!$B$13)+Annahmen!$B$15*(1+(B6-3)/2*Annahmen!$B$16)*(1+Annahmen!$B$25*(L6-Annahmen!$B$26)) -> 140.02536 | D6: =MIN(100,MAX(0,D5-Annahmen!$B$17*(B6-3)-Annahmen!$B$14*(D5-50)+Annahmen!$B$27*(L6-Annahmen!$B$26))) -> 25.115903 | E6: =E5+Annahmen!$B$12*(C6*Annahmen!$B$11*(D6/100)-E5) -> 15.749512 | F6: =C6*Annahmen!$B$10*(D6/100) -> 1.7584317 | G6: =E6*Annahmen!$B$9 -> 31.499025 | H6: =Annahmen!$B$18*Annahmen!$B$20*Annahmen!$B$19+Annahmen!$B$21+C6*Annahmen!$B$22 -> 88.400254 | I6: =F6+G6-H6 -> -55.142797 | J6: =J5+I6 -> 244.30369 | K6: =AVERAGE(B2:B5) -> 5 | L6: =ABS(B6-K6) -> 0
A7: 6 | B7: 5 | C7: =C6*(1-Annahmen!$B$13)+Annahmen!$B$15*(1+(B7-3)/2*Annahmen!$B$16)*(1+Annahmen!$B$25*(L7-Annahmen!$B$26)) -> 147.3246 | D7: =MIN(100,MAX(0,D6-Annahmen!$B$17*(B7-3)-Annahmen!$B$14*(D6-50)+Annahmen!$B$27*(L7-Annahmen!$B$26))) -> 20.860108 | E7: =E6+Annahmen!$B$12*(C7*Annahmen!$B$11*(D7/100)-E6) -> 14.770029 | F7: =C7*Annahmen!$B$10*(D7/100) -> 1.5366035 | G7: =E7*Annahmen!$B$9 -> 29.540057 | H7: =Annahmen!$B$18*Annahmen!$B$20*Annahmen!$B$19+Annahmen!$B$21+C7*Annahmen!$B$22 -> 88.473246 | I7: =F7+G7-H7 -> -57.396585 | J7: =J6+I7 -> 186.9071 | K7: =AVERAGE(B2:B6) -> 5 | L7: =ABS(B7-K7) -> 0
A8: 7 | B8: 5 | C8: =C7*(1-Annahmen!$B$13)+Annahmen!$B$15*(1+(B8-3)/2*Annahmen!$B$16)*(1+Annahmen!$B$25*(L8-Annahmen!$B$26)) -> 154.40486 | D8: =MIN(100,MAX(0,D7-Annahmen!$B$17*(B8-3)-Annahmen!$B$14*(D7-50)+Annahmen!$B$27*(L8-Annahmen!$B$26))) -> 16.817103 | E8: =E7+Annahmen!$B$12*(C8*Annahmen!$B$11*(D8/100)-E7) -> 13.723013 | F8: =C8*Annahmen!$B$10*(D8/100) -> 1.2983212 | G8: =E8*Annahmen!$B$9 -> 27.446027 | H8: =Annahmen!$B$18*Annahmen!$B$20*Annahmen!$B$19+Annahmen!$B$21+C8*Annahmen!$B$22 -> 88.544049 | I8: =F8+G8-H8 -> -59.799701 | J8: =J7+I8 -> 127.1074 | K8: =AVERAGE(B3:B7) -> 5 | L8: =ABS(B8-K8) -> 0
A9: 8 | B9: 5 | C9: =C8*(1-Annahmen!$B$13)+Annahmen!$B$15*(1+(B9-3)/2*Annahmen!$B$16)*(1+Annahmen!$B$25*(L9-Annahmen!$B$26)) -> 161.27271 | D9: =MIN(100,MAX(0,D8-Annahmen!$B$17*(B9-3)-Annahmen!$B$14*(D8-50)+Annahmen!$B$27*(L9-Annahmen!$B$26))) -> 12.976247 | E9: =E8+Annahmen!$B$12*(C9*Annahmen!$B$11*(D9/100)-E8) -> 12.606283 | F9: =C9*Annahmen!$B$10*(D9/100) -> 1.0463573 | G9: =E9*Annahmen!$B$9 -> 25.212566 | H9: =Annahmen!$B$18*Annahmen!$B$20*Annahmen!$B$19+Annahmen!$B$21+C9*Annahmen!$B$22 -> 88.612727 | I9: =F9+G9-H9 -> -62.353804 | J9: =J8+I9 -> 64.753599 | K9: =AVERAGE(B4:B8) -> 5 | L9: =ABS(B9-K9) -> 0
A10: 9 | B10: 5 | C10: =C9*(1-Annahmen!$B$13)+Annahmen!$B$15*(1+(B10-3)/2*Annahmen!$B$16)*(1+Annahmen!$B$25*(L10-Annahmen!$B$26)) -> 167.93453 | D10: =MIN(100,MAX(0,D9-Annahmen!$B$17*(B10-3)-Annahmen!$B$14*(D9-50)+Annahmen!$B$27*(L10-Annahmen!$B$26))) -> 9.3274351 | E10: =E9+Annahmen!$B$12*(C10*Annahmen!$B$11*(D10/100)-E9) -> 11.42022 | F10: =C10*Annahmen!$B$10*(D10/100) -> 0.78319923 | G10: =E10*Annahmen!$B$9 -> 22.84044 | H10: =Annahmen!$B$18*Annahmen!$B$20*Annahmen!$B$19+Annahmen!$B$21+C10*Annahmen!$B$22 -> 88.679345 | I10: =F10+G10-H10 -> -65.055706 | J10: =J9+I10 -> -0.30210708 | K10: =AVERAGE(B5:B9) -> 5 | L10: =ABS(B10-K10) -> 0
A11: 10 | B11: 5 | C11: =C10*(1-Annahmen!$B$13)+Annahmen!$B$15*(1+(B11-3)/2*Annahmen!$B$16)*(1+Annahmen!$B$25*(L11-Annahmen!$B$26)) -> 174.3965 | D11: =MIN(100,MAX(0,D10-Annahmen!$B$17*(B11-3)-Annahmen!$B$14*(D10-50)+Annahmen!$B$27*(L11-Annahmen!$B$26))) -> 5.8610633 | E11: =E10+Annahmen!$B$12*(C11*Annahmen!$B$11*(D11/100)-E10) -> 10.167154 | F11: =C11*Annahmen!$B$10*(D11/100) -> 0.51107446 | G11: =E11*Annahmen!$B$9 -> 20.334308 | H11: =Annahmen!$B$18*Annahmen!$B$20*Annahmen!$B$19+Annahmen!$B$21+C11*Annahmen!$B$22 -> 88.743965 | I11: =F11+G11-H11 -> -67.898583 | J11: =J10+I11 -> -68.20069 | K11: =AVERAGE(B6:B10) -> 5 | L11: =ABS(B11-K11) -> 0
A12: 11 | B12: 5 | C12: =C11*(1-Annahmen!$B$13)+Annahmen!$B$15*(1+(B12-3)/2*Annahmen!$B$16)*(1+Annahmen!$B$25*(L12-Annahmen!$B$26)) -> 180.6646 | D12: =MIN(100,MAX(0,D11-Annahmen!$B$17*(B12-3)-Annahmen!$B$14*(D11-50)+Annahmen!$B$27*(L12-Annahmen!$B$26))) -> 2.5680102 | E12: =E11+Annahmen!$B$12*(C12*Annahmen!$B$11*(D12/100)-E11) -> 8.8508576 | F12: =C12*Annahmen!$B$10*(D12/100) -> 0.23197427 | G12: =E12*Annahmen!$B$9 -> 17.701715 | H12: =Annahmen!$B$18*Annahmen!$B$20*Annahmen!$B$19+Annahmen!$B$21+C12*Annahmen!$B$22 -> 88.806646 | I12: =F12+G12-H12 -> -70.872957 | J12: =J11+I12 -> -139.07365 | K12: =AVERAGE(B7:B11) -> 5 | L12: =ABS(B12-K12) -> 0
A13: 12 | B13: 5 | C13: =C12*(1-Annahmen!$B$13)+Annahmen!$B$15*(1+(B13-3)/2*Annahmen!$B$16)*(1+Annahmen!$B$25*(L13-Annahmen!$B$26)) -> 186.74466 | D13: =MIN(100,MAX(0,D12-Annahmen!$B$17*(B13-3)-Annahmen!$B$14*(D12-50)+Annahmen!$B$27*(L13-Annahmen!$B$26))) -> 0 | E13: =E12+Annahmen!$B$12*(C13*Annahmen!$B$11*(D13/100)-E12) -> 7.523229 | F13: =C13*Annahmen!$B$10*(D13/100) -> 0 | G13: =E13*Annahmen!$B$9 -> 15.046458 | H13: =Annahmen!$B$18*Annahmen!$B$20*Annahmen!$B$19+Annahmen!$B$21+C13*Annahmen!$B$22 -> 88.867447 | I13: =F13+G13-H13 -> -73.820989 | J13: =J12+I13 -> -212.89464 | K13: =AVERAGE(B8:B12) -> 5 | L13: =ABS(B13-K13) -> 0
A14: 13 | B14: 5 | C14: =C13*(1-Annahmen!$B$13)+Annahmen!$B$15*(1+(B14-3)/2*Annahmen!$B$16)*(1+Annahmen!$B$25*(L14-Annahmen!$B$26)) -> 192.64232 | D14: =MIN(100,MAX(0,D13-Annahmen!$B$17*(B14-3)-Annahmen!$B$14*(D13-50)+Annahmen!$B$27*(L14-Annahmen!$B$26))) -> 0 | E14: =E13+Annahmen!$B$12*(C14*Annahmen!$B$11*(D14/100)-E13) -> 6.3947446 | F14: =C14*Annahmen!$B$10*(D14/100) -> 0 | G14: =E14*Annahmen!$B$9 -> 12.789489 | H14: =Annahmen!$B$18*Annahmen!$B$20*Annahmen!$B$19+Annahmen!$B$21+C14*Annahmen!$B$22 -> 88.926423 | I14: =F14+G14-H14 -> -76.136934 | J14: =J13+I14 -> -289.03157 | K14: =AVERAGE(B9:B13) -> 5 | L14: =ABS(B14-K14) -> 0
A15: 14 | B15: 5 | C15: =C14*(1-Annahmen!$B$13)+Annahmen!$B$15*(1+(B15-3)/2*Annahmen!$B$16)*(1+Annahmen!$B$25*(L15-Annahmen!$B$26)) -> 198.36305 | D15: =MIN(100,MAX(0,D14-Annahmen!$B$17*(B15-3)-Annahmen!$B$14*(D14-50)+Annahmen!$B$27*(L15-Annahmen!$B$26))) -> 0 | E15: =E14+Annahmen!$B$12*(C15*Annahmen!$B$11*(D15/100)-E14) -> 5.4355329 | F15: =C15*Annahmen!$B$10*(D15/100) -> 0 | G15: =E15*Annahmen!$B$9 -> 10.871066 | H15: =Annahmen!$B$18*Annahmen!$B$20*Annahmen!$B$19+Annahmen!$B$21+C15*Annahmen!$B$22 -> 88.983631 | I15: =F15+G15-H15 -> -78.112565 | J15: =J14+I15 -> -367.14413 | K15: =AVERAGE(B10:B14) -> 5 | L15: =ABS(B15-K15) -> 0
A16: 15 | B16: 5 | C16: =C15*(1-Annahmen!$B$13)+Annahmen!$B$15*(1+(B16-3)/2*Annahmen!$B$16)*(1+Annahmen!$B$25*(L16-Annahmen!$B$26)) -> 203.91216 | D16: =MIN(100,MAX(0,D15-Annahmen!$B$17*(B16-3)-Annahmen!$B$14*(D15-50)+Annahmen!$B$27*(L16-Annahmen!$B$26))) -> 0 | E16: =E15+Annahmen!$B$12*(C16*Annahmen!$B$11*(D16/100)-E15) -> 4.620203 | F16: =C16*Annahmen!$B$10*(D16/100) -> 0 | G16: =E16*Annahmen!$B$9 -> 9.240406 | H16: =Annahmen!$B$18*Annahmen!$B$20*Annahmen!$B$19+Annahmen!$B$21+C16*Annahmen!$B$22 -> 89.039122 | I16: =F16+G16-H16 -> -79.798716 | J16: =J15+I16 -> -446.94285 | K16: =AVERAGE(B11:B15) -> 5 | L16: =ABS(B16-K16) -> 0
A17: 16 | B17: 5 | C17: =C16*(1-Annahmen!$B$13)+Annahmen!$B$15*(1+(B17-3)/2*Annahmen!$B$16)*(1+Annahmen!$B$25*(L17-Annahmen!$B$26)) -> 209.2948 | D17: =MIN(100,MAX(0,D16-Annahmen!$B$17*(B17-3)-Annahmen!$B$14*(D16-50)+Annahmen!$B$27*(L17-Annahmen!$B$26))) -> 0 | E17: =E16+Annahmen!$B$12*(C17*Annahmen!$B$11*(D17/100)-E16) -> 3.9271725 | F17: =C17*Annahmen!$B$10*(D17/100) -> 0 | G17: =E17*Annahmen!$B$9 -> 7.8543451 | H17: =Annahmen!$B$18*Annahmen!$B$20*Annahmen!$B$19+Annahmen!$B$21+C17*Annahmen!$B$22 -> 89.092948 | I17: =F17+G17-H17 -> -81.238603 | J17: =J16+I17 -> -528.18145 | K17: =AVERAGE(B12:B16) -> 5 | L17: =ABS(B17-K17) -> 0
A18: 17 | B18: 5 | C18: =C17*(1-Annahmen!$B$13)+Annahmen!$B$15*(1+(B18-3)/2*Annahmen!$B$16)*(1+Annahmen!$B$25*(L18-Annahmen!$B$26)) -> 214.51595 | D18: =MIN(100,MAX(0,D17-Annahmen!$B$17*(B18-3)-Annahmen!$B$14*(D17-50)+Annahmen!$B$27*(L18-Annahmen!$B$26))) -> 0 | E18: =E17+Annahmen!$B$12*(C18*Annahmen!$B$11*(D18/100)-E17) -> 3.3380967 | F18: =C18*Annahmen!$B$10*(D18/100) -> 0 | G18: =E18*Annahmen!$B$9 -> 6.6761933 | H18: =Annahmen!$B$18*Annahmen!$B$20*Annahmen!$B$19+Annahmen!$B$21+C18*Annahmen!$B$22 -> 89.14516 | I18: =F18+G18-H18 -> -82.468966 | J18: =J17+I18 -> -610.65042 | K18: =AVERAGE(B13:B17) -> 5 | L18: =ABS(B18-K18) -> 0
... A101: 100 | B101: 5 | C101: =C100*(1-Annahmen!$B$13)+Annahmen!$B$15*(1+(B101-3)/2*Annahmen!$B$16)*(1+Annahmen!$B$25*(L101-Annahmen!$B$26)) -> 369.86012 | D101: =MIN(100,MAX(0,D100-Annahmen!$B$17*(B101-3)-Annahmen!$B$14*(D100-50)+Annahmen!$B$27*(L101-Annahmen!$B$26))) -> 0 | E101: =E100+Annahmen!$B$12*(C101*Annahmen!$B$11*(D101/100)-E100) -> 4.626683e-06 | F101: =C101*Annahmen!$B$10*(D101/100) -> 0 | G101: =E101*Annahmen!$B$9 -> 9.253366e-06 | H101: =Annahmen!$B$18*Annahmen!$B$20*Annahmen!$B$19+Annahmen!$B$21+C101*Annahmen!$B$22 -> 90.698601 | I101: =F101+G101-H101 -> -90.698592 | J101: =J100+I101 -> -8061.7574 | K101: =AVERAGE(B96:B100) -> 5 | L101: =ABS(B101-K101) -> 0

Sheet Sim_Investigativ
A1: Tag | B1: Boulevard-Grad | C1: Reichweite | D1: Reputation | E1: Abonnenten | F1: Werbe-Erlös | G1: Abo-Erlös | H1: Kosten | I1: Gewinn | J1: Kontostand | K1: Gleitender Ø-Grad | L1: Abwechslung |Grad-Ø|
A2: 1 | B2: 1 | C2: =Annahmen!$B$6*(1-Annahmen!$B$13)+Annahmen!$B$15*(1+(B2-3)/2*Annahmen!$B$16)*(1+Annahmen!$B$25*(L2-Annahmen!$B$26)) -> 105.5 | D2: =MIN(100,MAX(0,Annahmen!$B$7-Annahmen!$B$17*(B2-3)-Annahmen!$B$14*(Annahmen!$B$7-50)+Annahmen!$B$27*(L2-Annahmen!$B$26))) -> 50.5 | E2: =Annahmen!$B$8+Annahmen!$B$12*(C2*Annahmen!$B$11*(D2/100)-Annahmen!$B$8) -> 19.397488 | F2: =C2*Annahmen!$B$10*(D2/100) -> 2.663875 | G2: =E2*Annahmen!$B$9 -> 38.794975 | H2: =Annahmen!$B$18*Annahmen!$B$20*Annahmen!$B$19+Annahmen!$B$21+C2*Annahmen!$B$22 -> 88.055 | I2: =F2+G2-H2 -> -46.59615 | J2: =Annahmen!$B$5+I2 -> 453.40385 | K2: 0 | L2: 0
A3: 2 | B3: 1 | C3: =C2*(1-Annahmen!$B$13)+Annahmen!$B$15*(1+(B3-3)/2*Annahmen!$B$16)*(1+Annahmen!$B$25*(L3-Annahmen!$B$26)) -> 110.835 | D3: =MIN(100,MAX(0,D2-Annahmen!$B$17*(B3-3)-Annahmen!$B$14*(D2-50)+Annahmen!$B$27*(L3-Annahmen!$B$26))) -> 50.975 | E3: =E2+Annahmen!$B$12*(C3*Annahmen!$B$11*(D3/100)-E2) -> 19.030281 | F3: =C3*Annahmen!$B$10*(D3/100) -> 2.8249071 | G3: =E3*Annahmen!$B$9 -> 38.060561 | H3: =Annahmen!$B$18*Annahmen!$B$20*Annahmen!$B$19+Annahmen!$B$21+C3*Annahmen!$B$22 -> 88.10835 | I3: =F3+G3-H3 -> -47.222881 | J3: =J2+I3 -> 406.18097 | K3: =AVERAGE(B2:B2) -> 1 | L3: =ABS(B3-K3) -> 0
A4: 3 | B4: 1 | C4: =C3*(1-Annahmen!$B$13)+Annahmen!$B$15*(1+(B4-3)/2*Annahmen!$B$16)*(1+Annahmen!$B$25*(L4-Annahmen!$B$26)) -> 116.00995 | D4: =MIN(100,MAX(0,D3-Annahmen!$B$17*(B4-3)-Annahmen!$B$14*(D3-50)+Annahmen!$B$27*(L4-Annahmen!$B$26))) -> 51.42625 | E4: =E3+Annahmen!$B$12*(C4*Annahmen!$B$11*(D4/100)-E3) -> 18.860419 | F4: =C4*Annahmen!$B$10*(D4/100) -> 2.9829783 | G4: =E4*Annahmen!$B$9 -> 37.720838 | H4: =Annahmen!$B$18*Annahmen!$B$20*Annahmen!$B$19+Annahmen!$B$21+C4*Annahmen!$B$22 -> 88.1601 | I4: =F4+G4-H4 -> -47.456283 | J4: =J3+I4 -> 358.72469 | K4: =AVERAGE(B2:B3) -> 1 | L4: =ABS(B4-K4) -> 0
A5: 4 | B5: 1 | C5: =C4*(1-Annahmen!$B$13)+Annahmen!$B$15*(1+(B5-3)/2*Annahmen!$B$16)*(1+Annahmen!$B$25*(L5-Annahmen!$B$26)) -> 121.02965 | D5: =MIN(100,MAX(0,D4-Annahmen!$B$17*(B5-3)-Annahmen!$B$14*(D4-50)+Annahmen!$B$27*(L5-Annahmen!$B$26))) -> 51.854937 | E5: =E4+Annahmen!$B$12*(C5*Annahmen!$B$11*(D5/100)-E4) -> 18.85555 | F5: =C5*Annahmen!$B$10*(D5/100) -> 3.1379925 | G5: =E5*Annahmen!$B$9 -> 37.711099 | H5: =Annahmen!$B$18*Annahmen!$B$20*Annahmen!$B$19+Annahmen!$B$21+C5*Annahmen!$B$22 -> 88.210297 | I5: =F5+G5-H5 -> -47.361205 | J5: =J4+I5 -> 311.36348 | K5: =AVERAGE(B2:B4) -> 1 | L5: =ABS(B5-K5) -> 0
A6: 5 | B6: 1 | C6: =C5*(1-Annahmen!$B$13)+Annahmen!$B$15*(1+(B6-3)/2*Annahmen!$B$16)*(1+Annahmen!$B$25*(L6-Annahmen!$B$26)) -> 125.89876 | D6: =MIN(100,MAX(0,D5-Annahmen!$B$17*(B6-3)-Annahmen!$B$14*(D5-50)+Annahmen!$B$27*(L6-Annahmen!$B$26))) -> 52.262191 | E6: =E5+Annahmen!$B$12*(C6*Annahmen!$B$11*(D6/100)-E5) -> 18.988102 | F6: =C6*Annahmen!$B$10*(D6/100) -> 3.2898725 | G6: =E6*Annahmen!$B$9 -> 37.976205 | H6: =Annahmen!$B$18*Annahmen!$B$20*Annahmen!$B$19+Annahmen!$B$21+C6*Annahmen!$B$22 -> 88.258988 | I6: =F6+G6-H6 -> -46.99291 | J6: =J5+I6 -> 264.37057 | K6: =AVERAGE(B2:B5) -> 1 | L6: =ABS(B6-K6) -> 0
A7: 6 | B7: 1 | C7: =C6*(1-Annahmen!$B$13)+Annahmen!$B$15*(1+(B7-3)/2*Annahmen!$B$16)*(1+Annahmen!$B$25*(L7-Annahmen!$B$26)) -> 130.6218 | D7: =MIN(100,MAX(0,D6-Annahmen!$B$17*(B7-3)-Annahmen!$B$14*(D6-50)+Annahmen!$B$27*(L7-Annahmen!$B$26))) -> 52.649081 | E7: =E6+Annahmen!$B$12*(C7*Annahmen!$B$11*(D7/100)-E6) -> 19.23459 | F7: =C7*Annahmen!$B$10*(D7/100) -> 3.4385588 | G7: =E7*Annahmen!$B$9 -> 38.46918 | H7: =Annahmen!$B$18*Annahmen!$B$20*Annahmen!$B$19+Annahmen!$B$21+C7*Annahmen!$B$22 -> 88.306218 | I7: =F7+G7-H7 -> -46.398479 | J7: =J6+I7 -> 217.97209 | K7: =AVERAGE(B2:B6) -> 1 | L7: =ABS(B7-K7) -> 0
A8: 7 | B8: 1 | C8: =C7*(1-Annahmen!$B$13)+Annahmen!$B$15*(1+(B8-3)/2*Annahmen!$B$16)*(1+Annahmen!$B$25*(L8-Annahmen!$B$26)) -> 135.20315 | D8: =MIN(100,MAX(0,D7-Annahmen!$B$17*(B8-3)-Annahmen!$B$14*(D7-50)+Annahmen!$B$27*(L8-Annahmen!$B$26))) -> 53.016627 | E8: =E7+Annahmen!$B$12*(C8*Annahmen!$B$11*(D8/100)-E7) -> 19.575008 | F8: =C8*Annahmen!$B$10*(D8/100) -> 3.5840074 | G8: =E8*Annahmen!$B$9 -> 39.150016 | H8: =Annahmen!$B$18*Annahmen!$B$20*Annahmen!$B$19+Annahmen!$B$21+C8*Annahmen!$B$22 -> 88.352031 | I8: =F8+G8-H8 -> -45.618008 | J8: =J7+I8 -> 172.35408 | K8: =AVERAGE(B3:B7) -> 1 | L8: =ABS(B8-K8) -> 0
A9: 8 | B9: 1 | C9: =C8*(1-Annahmen!$B$13)+Annahmen!$B$15*(1+(B9-3)/2*Annahmen!$B$16)*(1+Annahmen!$B$25*(L9-Annahmen!$B$26)) -> 139.64705 | D9: =MIN(100,MAX(0,D8-Annahmen!$B$17*(B9-3)-Annahmen!$B$14*(D8-50)+Annahmen!$B$27*(L9-Annahmen!$B$26))) -> 53.365796 | E9: =E8+Annahmen!$B$12*(C9*Annahmen!$B$11*(D9/100)-E8) -> 19.992326 | F9: =C9*Annahmen!$B$10*(D9/100) -> 3.726188 | G9: =E9*Annahmen!$B$9 -> 39.984652 | H9: =Annahmen!$B$18*Annahmen!$B$20*Annahmen!$B$19+Annahmen!$B$21+C9*Annahmen!$B$22 -> 88.396471 | I9: =F9+G9-H9 -> -44.68563 | J9: =J8+I9 -> 127.66845 | K9: =AVERAGE(B4:B8) -> 1 | L9: =ABS(B9-K9) -> 0
A10: 9 | B10: 1 | C10: =C9*(1-Annahmen!$B$13)+Annahmen!$B$15*(1+(B10-3)/2*Annahmen!$B$16)*(1+Annahmen!$B$25*(L10-Annahmen!$B$26)) -> 143.95764 | D10: =MIN(100,MAX(0,D9-Annahmen!$B$17*(B10-3)-Annahmen!$B$14*(D9-50)+Annahmen!$B$27*(L10-Annahmen!$B$26))) -> 53.697506 | E10: =E9+Annahmen!$B$12*(C10*Annahmen!$B$11*(D10/100)-E9) -> 20.472052 | F10: =C10*Annahmen!$B$10*(D10/100) -> 3.8650831 | G10: =E10*Annahmen!$B$9 -> 40.944104 | H10: =Annahmen!$B$18*Annahmen!$B$20*Annahmen!$B$19+Annahmen!$B$21+C10*Annahmen!$B$22 -> 88.439576 | I10: =F10+G10-H10 -> -43.630389 | J10: =J9+I10 -> 84.038064 | K10: =AVERAGE(B5:B9) -> 1 | L10: =ABS(B10-K10) -> 0
A11: 10 | B11: 1 | C11: =C10*(1-Annahmen!$B$13)+Annahmen!$B$15*(1+(B11-3)/2*Annahmen!$B$16)*(1+Annahmen!$B$25*(L11-Annahmen!$B$26)) -> 148.13891 | D11: =MIN(100,MAX(0,D10-Annahmen!$B$17*(B11-3)-Annahmen!$B$14*(D10-50)+Annahmen!$B$27*(L11-Annahmen!$B$26))) -> 54.012631 | E11: =E10+Annahmen!$B$12*(C11*Annahmen!$B$11*(D11/100)-E10) -> 21.001862 | F11: =C11*Annahmen!$B$10*(D11/100) -> 4.0006861 | G11: =E11*Annahmen!$B$9 -> 42.003723 | H11: =Annahmen!$B$18*Annahmen!$B$20*Annahmen!$B$19+Annahmen!$B$21+C11*Annahmen!$B$22 -> 88.481389 | I11: =F11+G11-H11 -> -42.47698 | J11: =J10+I11 -> 41.561084 | K11: =AVERAGE(B6:B10) -> 1 | L11: =ABS(B11-K11) -> 0
A12: 11 | B12: 1 | C12: =C11*(1-Annahmen!$B$13)+Annahmen!$B$15*(1+(B12-3)/2*Annahmen!$B$16)*(1+Annahmen!$B$25*(L12-Annahmen!$B$26)) -> 152.19474 | D12: =MIN(100,MAX(0,D11-Annahmen!$B$17*(B12-3)-Annahmen!$B$14*(D11-50)+Annahmen!$B$27*(L12-Annahmen!$B$26))) -> 54.311999 | E12: =E11+Annahmen!$B$12*(C12*Annahmen!$B$11*(D12/100)-E11) -> 21.571283 | F12: =C12*Annahmen!$B$10*(D12/100) -> 4.1330004 | G12: =E12*Annahmen!$B$9 -> 43.142565 | H12: =Annahmen!$B$18*Annahmen!$B$20*Annahmen!$B$19+Annahmen!$B$21+C12*Annahmen!$B$22 -> 88.521947 | I12: =F12+G12-H12 -> -41.246382 | J12: =J11+I12 -> 0.31470238 | K12: =AVERAGE(B7:B11) -> 1 | L12: =ABS(B12-K12) -> 0
A13: 12 | B13: 1 | C13: =C12*(1-Annahmen!$B$13)+Annahmen!$B$15*(1+(B13-3)/2*Annahmen!$B$16)*(1+Annahmen!$B$25*(L13-Annahmen!$B$26)) -> 156.1289 | D13: =MIN(100,MAX(0,D12-Annahmen!$B$17*(B13-3)-Annahmen!$B$14*(D12-50)+Annahmen!$B$27*(L13-Annahmen!$B$26))) -> 54.596399 | E13: =E12+Annahmen!$B$12*(C13*Annahmen!$B$11*(D13/100)-E12) -> 22.171424 | F13: =C13*Annahmen!$B$10*(D13/100) -> 4.2620379 | G13: =E13*Annahmen!$B$9 -> 44.342849 | H13: =Annahmen!$B$18*Annahmen!$B$20*Annahmen!$B$19+Annahmen!$B$21+C13*Annahmen!$B$22 -> 88.561289 | I13: =F13+G13-H13 -> -39.956402 | J13: =J12+I13 -> -39.6417 | K13: =AVERAGE(B8:B12) -> 1 | L13: =ABS(B13-K13) -> 0
A14: 13 | B14: 1 | C14: =C13*(1-Annahmen!$B$13)+Annahmen!$B$15*(1+(B14-3)/2*Annahmen!$B$16)*(1+Annahmen!$B$25*(L14-Annahmen!$B$26)) -> 159.94503 | D14: =MIN(100,MAX(0,D13-Annahmen!$B$17*(B14-3)-Annahmen!$B$14*(D13-50)+Annahmen!$B$27*(L14-Annahmen!$B$26))) -> 54.866579 | E14: =E13+Annahmen!$B$12*(C14*Annahmen!$B$11*(D14/100)-E13) -> 22.794747 | F14: =C14*Annahmen!$B$10*(D14/100) -> 4.3878184 | G14: =E14*Annahmen!$B$9 -> 45.589495 | H14: =Annahmen!$B$18*Annahmen!$B$20*Annahmen!$B$19+Annahmen!$B$21+C14*Annahmen!$B$22 -> 88.59945 | I14: =F14+G14-H14 -> -38.622137 | J14: =J13+I14 -> -78.263837 | K14: =AVERAGE(B9:B13) -> 1 | L14: =ABS(B14-K14) -> 0
A15: 14 | B15: 1 | C15: =C14*(1-Annahmen!$B$13)+Annahmen!$B$15*(1+(B15-3)/2*Annahmen!$B$16)*(1+Annahmen!$B$25*(L15-Annahmen!$B$26)) -> 163.64668 | D15: =MIN(100,MAX(0,D14-Annahmen!$B$17*(B15-3)-Annahmen!$B$14*(D14-50)+Annahmen!$B$27*(L15-Annahmen!$B$26))) -> 55.12325 | E15: =E14+Annahmen!$B$12*(C15*Annahmen!$B$11*(D15/100)-E14) -> 23.434867 | F15: =C15*Annahmen!$B$10*(D15/100) -> 4.5103685 | G15: =E15*Annahmen!$B$9 -> 46.869734 | H15: =Annahmen!$B$18*Annahmen!$B$20*Annahmen!$B$19+Annahmen!$B$21+C15*Annahmen!$B$22 -> 88.636467 | I15: =F15+G15-H15 -> -37.256365 | J15: =J14+I15 -> -115.5202 | K15: =AVERAGE(B10:B14) -> 1 | L15: =ABS(B15-K15) -> 0
A16: 15 | B16: 1 | C16: =C15*(1-Annahmen!$B$13)+Annahmen!$B$15*(1+(B16-3)/2*Annahmen!$B$16)*(1+Annahmen!$B$25*(L16-Annahmen!$B$26)) -> 167.23728 | D16: =MIN(100,MAX(0,D15-Annahmen!$B$17*(B16-3)-Annahmen!$B$14*(D15-50)+Annahmen!$B$27*(L16-Annahmen!$B$26))) -> 55.367088 | E16: =E15+Annahmen!$B$12*(C16*Annahmen!$B$11*(D16/100)-E15) -> 24.086385 | F16: =C16*Annahmen!$B$10*(D16/100) -> 4.6297206 | G16: =E16*Annahmen!$B$9 -> 48.172771 | H16: =Annahmen!$B$18*Annahmen!$B$20*Annahmen!$B$19+Annahmen!$B$21+C16*Annahmen!$B$22 -> 88.672373 | I16: =F16+G16-H16 -> -35.869881 | J16: =J15+I16 -> -151.39008 | K16: =AVERAGE(B11:B15) -> 1 | L16: =ABS(B16-K16) -> 0
A17: 16 | B17: 1 | C17: =C16*(1-Annahmen!$B$13)+Annahmen!$B$15*(1+(B17-3)/2*Annahmen!$B$16)*(1+Annahmen!$B$25*(L17-Annahmen!$B$26)) -> 170.72016 | D17: =MIN(100,MAX(0,D16-Annahmen!$B$17*(B17-3)-Annahmen!$B$14*(D16-50)+Annahmen!$B$27*(L17-Annahmen!$B$26))) -> 55.598733 | E17: =E16+Annahmen!$B$12*(C17*Annahmen!$B$11*(D17/100)-E16) -> 24.744749 | F17: =C17*Annahmen!$B$10*(D17/100) -> 4.7459124 | G17: =E17*Annahmen!$B$9 -> 49.489498 | H17: =Annahmen!$B$18*Annahmen!$B$20*Annahmen!$B$19+Annahmen!$B$21+C17*Annahmen!$B$22 -> 88.707202 | I17: =F17+G17-H17 -> -34.471792 | J17: =J16+I17 -> -185.86187 | K17: =AVERAGE(B12:B16) -> 1 | L17: =ABS(B17-K17) -> 0
A18: 17 | B18: 1 | C18: =C17*(1-Annahmen!$B$13)+Annahmen!$B$15*(1+(B18-3)/2*Annahmen!$B$16)*(1+Annahmen!$B$25*(L18-Annahmen!$B$26)) -> 174.09856 | D18: =MIN(100,MAX(0,D17-Annahmen!$B$17*(B18-3)-Annahmen!$B$14*(D17-50)+Annahmen!$B$27*(L18-Annahmen!$B$26))) -> 55.818797 | E18: =E17+Annahmen!$B$12*(C18*Annahmen!$B$11*(D18/100)-E17) -> 25.406124 | F18: =C18*Annahmen!$B$10*(D18/100) -> 4.858986 | G18: =E18*Annahmen!$B$9 -> 50.812248 | H18: =Annahmen!$B$18*Annahmen!$B$20*Annahmen!$B$19+Annahmen!$B$21+C18*Annahmen!$B$22 -> 88.740986 | I18: =F18+G18-H18 -> -33.069752 | J18: =J17+I18 -> -218.93163 | K18: =AVERAGE(B13:B17) -> 1 | L18: =ABS(B18-K18) -> 0
... A101: 100 | B101: 1 | C101: =C100*(1-Annahmen!$B$13)+Annahmen!$B$15*(1+(B101-3)/2*Annahmen!$B$16)*(1+Annahmen!$B$25*(L101-Annahmen!$B$26)) -> 274.61537 | D101: =MIN(100,MAX(0,D100-Annahmen!$B$17*(B101-3)-Annahmen!$B$14*(D100-50)+Annahmen!$B$27*(L101-Annahmen!$B$26))) -> 59.940795 | E101: =E100+Annahmen!$B$12*(C101*Annahmen!$B$11*(D101/100)-E100) -> 49.028587 | F101: =C101*Annahmen!$B$10*(D101/100) -> 8.2303319 | G101: =E101*Annahmen!$B$9 -> 98.057175 | H101: =Annahmen!$B$18*Annahmen!$B$20*Annahmen!$B$19+Annahmen!$B$21+C101*Annahmen!$B$22 -> 89.746154 | I101: =F101+G101-H101 -> 16.541353 | J101: =J100+I101 -> -115.76123 | K101: =AVERAGE(B96:B100) -> 1 | L101: =ABS(B101-K101) -> 0

Sheet Sim_Gemischt
A1: Tag | B1: Boulevard-Grad | C1: Reichweite | D1: Reputation | E1: Abonnenten | F1: Werbe-Erlös | G1: Abo-Erlös | H1: Kosten | I1: Gewinn | J1: Kontostand | K1: Gleitender Ø-Grad | L1: Abwechslung |Grad-Ø|
A2: 1 | B2: =IF(MOD(A2,2)=0,5,1) -> 1 | C2: =Annahmen!$B$6*(1-Annahmen!$B$13)+Annahmen!$B$15*(1+(B2-3)/2*Annahmen!$B$16)*(1+Annahmen!$B$25*(L2-Annahmen!$B$26)) -> 105.5 | D2: =MIN(100,MAX(0,Annahmen!$B$7-Annahmen!$B$17*(B2-3)-Annahmen!$B$14*(Annahmen!$B$7-50)+Annahmen!$B$27*(L2-Annahmen!$B$26))) -> 50.5 | E2: =Annahmen!$B$8+Annahmen!$B$12*(C2*Annahmen!$B$11*(D2/100)-Annahmen!$B$8) -> 19.397488 | F2: =C2*Annahmen!$B$10*(D2/100) -> 2.663875 | G2: =E2*Annahmen!$B$9 -> 38.794975 | H2: =Annahmen!$B$18*Annahmen!$B$20*Annahmen!$B$19+Annahmen!$B$21+C2*Annahmen!$B$22 -> 88.055 | I2: =F2+G2-H2 -> -46.59615 | J2: =Annahmen!$B$5+I2 -> 453.40385 | K2: 0 | L2: 0
A3: 2 | B3: =IF(MOD(A3,2)=0,5,1) -> 5 | C3: =C2*(1-Annahmen!$B$13)+Annahmen!$B$15*(1+(B3-3)/2*Annahmen!$B$16)*(1+Annahmen!$B$25*(L3-Annahmen!$B$26)) -> 159.835 | D3: =MIN(100,MAX(0,D2-Annahmen!$B$17*(B3-3)-Annahmen!$B$14*(D2-50)+Annahmen!$B$27*(L3-Annahmen!$B$26))) -> 54.975 | E3: =E2+Annahmen!$B$12*(C3*Annahmen!$B$11*(D3/100)-E2) -> 20.441982 | F3: =C3*Annahmen!$B$10*(D3/100) -> 4.3934646 | G3: =E3*Annahmen!$B$9 -> 40.883965 | H3: =Annahmen!$B$18*Annahmen!$B$20*Annahmen!$B$19+Annahmen!$B$21+C3*Annahmen!$B$22 -> 88.59835 | I3: =F3+G3-H3 -> -43.32092 | J3: =J2+I3 -> 410.08293 | K3: =AVERAGE(B2:B2) -> 1 | L3: =ABS(B3-K3) -> 4
A4: 3 | B4: =IF(MOD(A4,2)=0,5,1) -> 1 | C4: =C3*(1-Annahmen!$B$13)+Annahmen!$B$15*(1+(B4-3)/2*Annahmen!$B$16)*(1+Annahmen!$B$25*(L4-Annahmen!$B$26)) -> 180.53995 | D4: =MIN(100,MAX(0,D3-Annahmen!$B$17*(B4-3)-Annahmen!$B$14*(D3-50)+Annahmen!$B$27*(L4-Annahmen!$B$26))) -> 60.22625 | E4: =E3+Annahmen!$B$12*(C4*Annahmen!$B$11*(D4/100)-E3) -> 22.268645 | F4: =C4*Annahmen!$B$10*(D4/100) -> 5.4366221 | G4: =E4*Annahmen!$B$9 -> 44.53729 | H4: =Annahmen!$B$18*Annahmen!$B$20*Annahmen!$B$19+Annahmen!$B$21+C4*Annahmen!$B$22 -> 88.805399 | I4: =F4+G4-H4 -> -38.831487 | J4: =J3+I4 -> 371.25144 | K4: =AVERAGE(B2:B3) -> 3 | L4: =ABS(B4-K4) -> 2
A5: 4 | B5: =IF(MOD(A5,2)=0,5,1) -> 5 | C5: =C4*(1-Annahmen!$B$13)+Annahmen!$B$15*(1+(B5-3)/2*Annahmen!$B$16)*(1+Annahmen!$B$25*(L5-Annahmen!$B$26)) -> 217.29042 | D5: =MIN(100,MAX(0,D4-Annahmen!$B$17*(B5-3)-Annahmen!$B$14*(D4-50)+Annahmen!$B$27*(L5-Annahmen!$B$26))) -> 60.881604 | E5: =E4+Annahmen!$B$12*(C5*Annahmen!$B$11*(D5/100)-E4) -> 24.881393 | F5: =C5*Annahmen!$B$10*(D5/100) -> 6.6144946 | G5: =E5*Annahmen!$B$9 -> 49.762787 | H5: =Annahmen!$B$18*Annahmen!$B$20*Annahmen!$B$19+Annahmen!$B$21+C5*Annahmen!$B$22 -> 89.172904 | I5: =F5+G5-H5 -> -32.795623 | J5: =J4+I5 -> 338.45582 | K5: =AVERAGE(B2:B4) -> 2.3333333 | L5: =ABS(B5-K5) -> 2.6666667
A6: 5 | B6: =IF(MOD(A6,2)=0,5,1) -> 1 | C6: =C5*(1-Annahmen!$B$13)+Annahmen!$B$15*(1+(B6-3)/2*Annahmen!$B$16)*(1+Annahmen!$B$25*(L6-Annahmen!$B$26)) -> 236.27171 | D6: =MIN(100,MAX(0,D5-Annahmen!$B$17*(B6-3)-Annahmen!$B$14*(D5-50)+Annahmen!$B$27*(L6-Annahmen!$B$26))) -> 65.837524 | E6: =E5+Annahmen!$B$12*(C6*Annahmen!$B$11*(D6/100)-E5) -> 28.149179 | F6: =C6*Annahmen!$B$10*(D6/100) -> 7.777772 | G6: =E6*Annahmen!$B$9 -> 56.298358 | H6: =Annahmen!$B$18*Annahmen!$B$20*Annahmen!$B$19+Annahmen!$B$21+C6*Annahmen!$B$22 -> 89.362717 | I6: =F6+G6-H6 -> -25.286587 | J6: =J5+I6 -> 313.16923 | K6: =AVERAGE(B2:B5) -> 3 | L6: =ABS(B6-K6) -> 2
A7: 6 | B7: =IF(MOD(A7,2)=0,5,1) -> 5 | C7: =C6*(1-Annahmen!$B$13)+Annahmen!$B$15*(1+(B7-3)/2*Annahmen!$B$16)*(1+Annahmen!$B$25*(L7-Annahmen!$B$26)) -> 268.28355 | D7: =MIN(100,MAX(0,D6-Annahmen!$B$17*(B7-3)-Annahmen!$B$14*(D6-50)+Annahmen!$B$27*(L7-Annahmen!$B$26))) -> 65.545648 | E7: =E6+Annahmen!$B$12*(C7*Annahmen!$B$11*(D7/100)-E6) -> 31.839971 | F7: =C7*Annahmen!$B$10*(D7/100) -> 8.7924097 | G7: =E7*Annahmen!$B$9 -> 63.679942 | H7: =Annahmen!$B$18*Annahmen!$B$20*Annahmen!$B$19+Annahmen!$B$21+C7*Annahmen!$B$22 -> 89.682836 | I7: =F7+G7-H7 -> -17.210484 | J7: =J6+I7 -> 295.95875 | K7: =AVERAGE(B2:B6) -> 2.6 | L7: =ABS(B7-K7) -> 2.4
A8: 7 | B8: =IF(MOD(A8,2)=0,5,1) -> 1 | C8: =C7*(1-Annahmen!$B$13)+Annahmen!$B$15*(1+(B8-3)/2*Annahmen!$B$16)*(1+Annahmen!$B$25*(L8-Annahmen!$B$26)) -> 289.13505 | D8: =MIN(100,MAX(0,D7-Annahmen!$B$17*(B8-3)-Annahmen!$B$14*(D7-50)+Annahmen!$B$27*(L8-Annahmen!$B$26))) -> 71.268365 | E8: =E7+Annahmen!$B$12*(C8*Annahmen!$B$11*(D8/100)-E7) -> 36.336757 | F8: =C8*Annahmen!$B$10*(D8/100) -> 10.303091 | G8: =E8*Annahmen!$B$9 -> 72.673515 | H8: =Annahmen!$B$18*Annahmen!$B$20*Annahmen!$B$19+Annahmen!$B$21+C8*Annahmen!$B$22 -> 89.89135 | I8: =F8+G8-H8 -> -6.9147446 | J8: =J7+I8 -> 289.044 | K8: =AVERAGE(B3:B7) -> 3.4 | L8: =ABS(B8-K8) -> 2.4
A9: 8 | B9: =IF(MOD(A9,2)=0,5,1) -> 5 | C9: =C8*(1-Annahmen!$B$13)+Annahmen!$B$15*(1+(B9-3)/2*Annahmen!$B$16)*(1+Annahmen!$B$25*(L9-Annahmen!$B$26)) -> 319.561 | D9: =MIN(100,MAX(0,D8-Annahmen!$B$17*(B9-3)-Annahmen!$B$14*(D8-50)+Annahmen!$B$27*(L9-Annahmen!$B$26))) -> 70.704947 | E9: =E8+Annahmen!$B$12*(C9*Annahmen!$B$11*(D9/100)-E8) -> 41.053788 | F9: =C9*Annahmen!$B$10*(D9/100) -> 11.297272 | G9: =E9*Annahmen!$B$9 -> 82.107577 | H9: =Annahmen!$B$18*Annahmen!$B$20*Annahmen!$B$19+Annahmen!$B$21+C9*Annahmen!$B$22 -> 90.19561 | I9: =F9+G9-H9 -> 3.2092383 | J9: =J8+I9 -> 292.25324 | K9: =AVERAGE(B4:B8) -> 2.6 | L9: =ABS(B9-K9) -> 2.4
A10: 9 | B10: =IF(MOD(A10,2)=0,5,1) -> 1 | C10: =C9*(1-Annahmen!$B$13)+Annahmen!$B$15*(1+(B10-3)/2*Annahmen!$B$16)*(1+Annahmen!$B$25*(L10-Annahmen!$B$26)) -> 338.87417 | D10: =MIN(100,MAX(0,D9-Annahmen!$B$17*(B10-3)-Annahmen!$B$14*(D9-50)+Annahmen!$B$27*(L10-Annahmen!$B$26))) -> 76.1697 | E10: =E9+Annahmen!$B$12*(C10*Annahmen!$B$11*(D10/100)-E9) -> 46.511095 | F10: =C10*Annahmen!$B$10*(D10/100) -> 12.905972 | G10: =E10*Annahmen!$B$9 -> 93.022189 | H10: =Annahmen!$B$18*Annahmen!$B$20*Annahmen!$B$19+Annahmen!$B$21+C10*Annahmen!$B$22 -> 90.388742 | I10: =F10+G10-H10 -> 15.539419 | J10: =J9+I10 -> 307.79266 | K10: =AVERAGE(B5:B9) -> 3.4 | L10: =ABS(B10-K10) -> 2.4
A11: 10 | B11: =IF(MOD(A11,2)=0,5,1) -> 5 | C11: =C10*(1-Annahmen!$B$13)+Annahmen!$B$15*(1+(B11-3)/2*Annahmen!$B$16)*(1+Annahmen!$B$25*(L11-Annahmen!$B$26)) -> 367.80794 | D11: =MIN(100,MAX(0,D10-Annahmen!$B$17*(B11-3)-Annahmen!$B$14*(D10-50)+Annahmen!$B$27*(L11-Annahmen!$B$26))) -> 75.361215 | E11: =E10+Annahmen!$B$12*(C11*Annahmen!$B$11*(D11/100)-E10) -> 52.007734 | F11: =C11*Annahmen!$B$10*(D11/100) -> 13.859227 | G11: =E11*Annahmen!$B$9 -> 104.01547 | H11: =Annahmen!$B$18*Annahmen!$B$20*Annahmen!$B$19+Annahmen!$B$21+C11*Annahmen!$B$22 -> 90.678079 | I11: =F11+G11-H11 -> 27.196616 | J11: =J10+I11 -> 334.98928 | K11: =AVERAGE(B6:B10) -> 2.6 | L11: =ABS(B11-K11) -> 2.4
A12: 11 | B12: =IF(MOD(A12,2)=0,5,1) -> 1 | C12: =C11*(1-Annahmen!$B$13)+Annahmen!$B$15*(1+(B12-3)/2*Annahmen!$B$16)*(1+Annahmen!$B$25*(L12-Annahmen!$B$26)) -> 385.6737 | D12: =MIN(100,MAX(0,D11-Annahmen!$B$17*(B12-3)-Annahmen!$B$14*(D11-50)+Annahmen!$B$27*(L12-Annahmen!$B$26))) -> 80.593154 | E12: =E11+Annahmen!$B$12*(C12*Annahmen!$B$11*(D12/100)-E11) -> 58.193771 | F12: =C12*Annahmen!$B$10*(D12/100) -> 15.54133 | G12: =E12*Annahmen!$B$9 -> 116.38754 | H12: =Annahmen!$B$18*Annahmen!$B$20*Annahmen!$B$19+Annahmen!$B$21+C12*Annahmen!$B$22 -> 90.856737 | I12: =F12+G12-H12 -> 41.072136 | J12: =J11+I12 -> 376.06141 | K12: =AVERAGE(B7:B11) -> 3.4 | L12: =ABS(B12-K12) -> 2.4
A13: 12 | B13: =IF(MOD(A13,2)=0,5,1) -> 5 | C13: =C12*(1-Annahmen!$B$13)+Annahmen!$B$15*(1+(B13-3)/2*Annahmen!$B$16)*(1+Annahmen!$B$25*(L13-Annahmen!$B$26)) -> 413.20349 | D13: =MIN(100,MAX(0,D12-Annahmen!$B$17*(B13-3)-Annahmen!$B$14*(D12-50)+Annahmen!$B$27*(L13-Annahmen!$B$26))) -> 79.563496 | E13: =E12+Annahmen!$B$12*(C13*Annahmen!$B$11*(D13/100)-E12) -> 64.258867 | F13: =C13*Annahmen!$B$10*(D13/100) -> 16.437957 | G13: =E13*Annahmen!$B$9 -> 128.51773 | H13: =Annahmen!$B$18*Annahmen!$B$20*Annahmen!$B$19+Annahmen!$B$21+C13*Annahmen!$B$22 -> 91.132035 | I13: =F13+G13-H13 -> 53.823657 | J13: =J12+I13 -> 429.88507 | K13: =AVERAGE(B8:B12) -> 2.6 | L13: =ABS(B13-K13) -> 2.4
A14: 13 | B14: =IF(MOD(A14,2)=0,5,1) -> 1 | C14: =C13*(1-Annahmen!$B$13)+Annahmen!$B$15*(1+(B14-3)/2*Annahmen!$B$16)*(1+Annahmen!$B$25*(L14-Annahmen!$B$26)) -> 429.70739 | D14: =MIN(100,MAX(0,D13-Annahmen!$B$17*(B14-3)-Annahmen!$B$14*(D13-50)+Annahmen!$B$27*(L14-Annahmen!$B$26))) -> 84.585322 | E14: =E13+Annahmen!$B$12*(C14*Annahmen!$B$11*(D14/100)-E13) -> 70.976159 | F14: =C14*Annahmen!$B$10*(D14/100) -> 18.173469 | G14: =E14*Annahmen!$B$9 -> 141.95232 | H14: =Annahmen!$B$18*Annahmen!$B$20*Annahmen!$B$19+Annahmen!$B$21+C14*Annahmen!$B$22 -> 91.297074 | I14: =F14+G14-H14 -> 68.828713 | J14: =J13+I14 -> 498.71378 | K14: =AVERAGE(B9:B13) -> 3.4 | L14: =ABS(B14-K14) -> 2.4
A15: 14 | B15: =IF(MOD(A15,2)=0,5,1) -> 5 | C15: =C14*(1-Annahmen!$B$13)+Annahmen!$B$15*(1+(B15-3)/2*Annahmen!$B$16)*(1+Annahmen!$B$25*(L15-Annahmen!$B$26)) -> 455.91617 | D15: =MIN(100,MAX(0,D14-Annahmen!$B$17*(B15-3)-Annahmen!$B$14*(D14-50)+Annahmen!$B$27*(L15-Annahmen!$B$26))) -> 83.356055 | E15: =E14+Annahmen!$B$12*(C15*Annahmen!$B$11*(D15/100)-E14) -> 77.431253 | F15: =C15*Annahmen!$B$10*(D15/100) -> 19.001687 | G15: =E15*Annahmen!$B$9 -> 154.86251 | H15: =Annahmen!$B$18*Annahmen!$B$20*Annahmen!$B$19+Annahmen!$B$21+C15*Annahmen!$B$22 -> 91.559162 | I15: =F15+G15-H15 -> 82.305031 | J15: =J14+I15 -> 581.01881 | K15: =AVERAGE(B10:B14) -> 2.6 | L15: =ABS(B15-K15) -> 2.4
A16: 15 | B16: =IF(MOD(A16,2)=0,5,1) -> 1 | C16: =C15*(1-Annahmen!$B$13)+Annahmen!$B$15*(1+(B16-3)/2*Annahmen!$B$16)*(1+Annahmen!$B$25*(L16-Annahmen!$B$26)) -> 471.13868 | D16: =MIN(100,MAX(0,D15-Annahmen!$B$17*(B16-3)-Annahmen!$B$14*(D15-50)+Annahmen!$B$27*(L16-Annahmen!$B$26))) -> 88.188253 | E16: =E15+Annahmen!$B$12*(C16*Annahmen!$B$11*(D16/100)-E15) -> 84.513569 | F16: =C16*Annahmen!$B$10*(D16/100) -> 20.774449 | G16: =E16*Annahmen!$B$9 -> 169.02714 | H16: =Annahmen!$B$18*Annahmen!$B$20*Annahmen!$B$19+Annahmen!$B$21+C16*Annahmen!$B$22 -> 91.711387 | I16: =F16+G16-H16 -> 98.090199 | J16: =J15+I16 -> 679.10901 | K16: =AVERAGE(B11:B15) -> 3.4 | L16: =ABS(B16-K16) -> 2.4
A17: 16 | B17: =IF(MOD(A17,2)=0,5,1) -> 5 | C17: =C16*(1-Annahmen!$B$13)+Annahmen!$B$15*(1+(B17-3)/2*Annahmen!$B$16)*(1+Annahmen!$B$25*(L17-Annahmen!$B$26)) -> 496.10452 | D17: =MIN(100,MAX(0,D16-Annahmen!$B$17*(B17-3)-Annahmen!$B$14*(D16-50)+Annahmen!$B$27*(L17-Annahmen!$B$26))) -> 86.77884 | E17: =E16+Annahmen!$B$12*(C17*Annahmen!$B$11*(D17/100)-E16) -> 91.209652 | F17: =C17*Annahmen!$B$10*(D17/100) -> 21.525687 | G17: =E17*Annahmen!$B$9 -> 182.4193 | H17: =Annahmen!$B$18*Annahmen!$B$20*Annahmen!$B$19+Annahmen!$B$21+C17*Annahmen!$B$22 -> 91.961045 | I17: =F17+G17-H17 -> 111.98395 | J17: =J16+I17 -> 791.09296 | K17: =AVERAGE(B12:B16) -> 2.6 | L17: =ABS(B17-K17) -> 2.4
A18: 17 | B18: =IF(MOD(A18,2)=0,5,1) -> 1 | C18: =C17*(1-Annahmen!$B$13)+Annahmen!$B$15*(1+(B18-3)/2*Annahmen!$B$16)*(1+Annahmen!$B$25*(L18-Annahmen!$B$26)) -> 510.12138 | D18: =MIN(100,MAX(0,D17-Annahmen!$B$17*(B18-3)-Annahmen!$B$14*(D17-50)+Annahmen!$B$27*(L18-Annahmen!$B$26))) -> 91.439898 | E18: =E17+Annahmen!$B$12*(C18*Annahmen!$B$11*(D18/100)-E17) -> 98.518656 | F18: =C18*Annahmen!$B$10*(D18/100) -> 23.322724 | G18: =E18*Annahmen!$B$9 -> 197.03731 | H18: =Annahmen!$B$18*Annahmen!$B$20*Annahmen!$B$19+Annahmen!$B$21+C18*Annahmen!$B$22 -> 92.101214 | I18: =F18+G18-H18 -> 128.25882 | J18: =J17+I18 -> 919.35178 | K18: =AVERAGE(B13:B17) -> 3.4 | L18: =ABS(B18-K18) -> 2.4
... A101: 100 | B101: =IF(MOD(A101,2)=0,5,1) -> 5 | C101: =C100*(1-Annahmen!$B$13)+Annahmen!$B$15*(1+(B101-3)/2*Annahmen!$B$16)*(1+Annahmen!$B$25*(L101-Annahmen!$B$26)) -> 1086.3906 | D101: =MIN(100,MAX(0,D100-Annahmen!$B$17*(B101-3)-Annahmen!$B$14*(D100-50)+Annahmen!$B$27*(L101-Annahmen!$B$26))) -> 98 | E101: =E100+Annahmen!$B$12*(C101*Annahmen!$B$11*(D101/100)-E100) -> 318.55381 | F101: =C101*Annahmen!$B$10*(D101/100) -> 53.23314 | G101: =E101*Annahmen!$B$9 -> 637.10763 | H101: =Annahmen!$B$18*Annahmen!$B$20*Annahmen!$B$19+Annahmen!$B$21+C101*Annahmen!$B$22 -> 97.863906 | I101: =F101+G101-H101 -> 592.47686 | J101: =J100+I101 -> 38998.139 | K101: =AVERAGE(B96:B100) -> 2.6 | L101: =ABS(B101-K101) -> 2.4

Sheet Vergleich
A1: Kontostand-Vergleich der drei Strategien über 100 Tage
A3: Tag | B3: Kontostand: Immer Boulevard | C3: Kontostand: Immer Investigativ | D3: Kontostand: Gemischt
A4: =Sim_Boulevard!A2 -> 1 | B4: =Sim_Boulevard!J2 -> 452.67455 | C4: =Sim_Investigativ!J2 -> 453.40385 | D4: =Sim_Gemischt!J2 -> 453.40385
A5: =Sim_Boulevard!A3 -> 2 | B5: =Sim_Boulevard!J3 -> 403.51994 | C5: =Sim_Investigativ!J3 -> 406.18097 | D5: =Sim_Gemischt!J3 -> 410.08293
A6: =Sim_Boulevard!A4 -> 3 | B6: =Sim_Boulevard!J4 -> 352.47683 | C6: =Sim_Investigativ!J4 -> 358.72469 | D6: =Sim_Gemischt!J4 -> 371.25144
A7: =Sim_Boulevard!A5 -> 4 | B7: =Sim_Boulevard!J5 -> 299.44649 | C7: =Sim_Investigativ!J5 -> 311.36348 | D7: =Sim_Gemischt!J5 -> 338.45582
A8: =Sim_Boulevard!A6 -> 5 | B8: =Sim_Boulevard!J6 -> 244.30369 | C8: =Sim_Investigativ!J6 -> 264.37057 | D8: =Sim_Gemischt!J6 -> 313.16923
A9: =Sim_Boulevard!A7 -> 6 | B9: =Sim_Boulevard!J7 -> 186.9071 | C9: =Sim_Investigativ!J7 -> 217.97209 | D9: =Sim_Gemischt!J7 -> 295.95875
A10: =Sim_Boulevard!A8 -> 7 | B10: =Sim_Boulevard!J8 -> 127.1074 | C10: =Sim_Investigativ!J8 -> 172.35408 | D10: =Sim_Gemischt!J8 -> 289.044
A11: =Sim_Boulevard!A9 -> 8 | B11: =Sim_Boulevard!J9 -> 64.753599 | C11: =Sim_Investigativ!J9 -> 127.66845 | D11: =Sim_Gemischt!J9 -> 292.25324
A12: =Sim_Boulevard!A10 -> 9 | B12: =Sim_Boulevard!J10 -> -0.30210708 | C12: =Sim_Investigativ!J10 -> 84.038064 | D12: =Sim_Gemischt!J10 -> 307.79266
A13: =Sim_Boulevard!A11 -> 10 | B13: =Sim_Boulevard!J11 -> -68.20069 | C13: =Sim_Investigativ!J11 -> 41.561084 | D13: =Sim_Gemischt!J11 -> 334.98928
A14: =Sim_Boulevard!A12 -> 11 | B14: =Sim_Boulevard!J12 -> -139.07365 | C14: =Sim_Investigativ!J12 -> 0.31470238 | D14: =Sim_Gemischt!J12 -> 376.06141
A15: =Sim_Boulevard!A13 -> 12 | B15: =Sim_Boulevard!J13 -> -212.89464 | C15: =Sim_Investigativ!J13 -> -39.6417 | D15: =Sim_Gemischt!J13 -> 429.88507
... A103: =Sim_Boulevard!A101 -> 100 | B103: =Sim_Boulevard!J101 -> -8061.7574 | C103: =Sim_Investigativ!J101 -> -115.76123 | D103: =Sim_Gemischt!J101 -> 38998.139
